{
  "generatedAt": "2026-04-27T19:05:48.761Z",
  "nodes": [
    {
      "nodeId": "NODE07",
      "deviceId": "ESP32-001",
      "gatewayId": "GW01",
      "name": "Laboratorio 1",
      "location": "Bloco A",
      "status": "offline",
      "seq": 10224,
      "rssi": -71,
      "battery": 3.91,
      "lastSeen": "2026-04-27T20:35:47.015Z",
      "samplingIntervalSec": 300
    },
    {
      "nodeId": "NODE08",
      "deviceId": "ESP32-002",
      "gatewayId": "GW01",
      "name": "Corredor",
      "location": "Bloco B",
      "status": "offline",
      "seq": 1657,
      "rssi": -49,
      "battery": 3.88,
      "lastSeen": "2026-04-27T20:36:37.035Z",
      "samplingIntervalSec": 300
    },
    {
      "nodeId": "NODE09",
      "deviceId": "ESP32-003",
      "gatewayId": "GW01",
      "name": "Sala de Servidores",
      "location": "Bloco C",
      "status": "offline",
      "seq": 2252,
      "rssi": -42,
      "battery": 3.77,
      "lastSeen": "2026-04-27T20:37:07.054Z",
      "samplingIntervalSec": 300
    },
    {
      "nodeId": "NODE10",
      "deviceId": "ESP32-004",
      "gatewayId": "GW01",
      "name": "Area Externa",
      "location": "Pátio",
      "status": "offline",
      "seq": 18184,
      "rssi": -78,
      "battery": 3.83,
      "lastSeen": "2026-05-13T08:37:59.792Z",
      "samplingIntervalSec": 300
    },
    {
      "nodeId": "NODE99",
      "deviceId": "ESP32-009",
      "gatewayId": "GW01",
      "name": "NODE99",
      "location": "indefinido",
      "status": "offline",
      "seq": 200,
      "rssi": -67,
      "battery": 3.89,
      "lastSeen": "2026-04-27T20:36:57.046Z",
      "samplingIntervalSec": 300
    },
    {
      "nodeId": "NODE_TEST",
      "deviceId": "ESP32-TEST",
      "gatewayId": "GW01",
      "name": "NODE_TEST",
      "location": "indefinido",
      "status": "offline",
      "seq": 488,
      "rssi": -58,
      "battery": 3.9,
      "lastSeen": "2026-04-28T14:46:06.014Z",
      "samplingIntervalSec": 300
    },
    {
      "nodeId": "NODE_TEST2",
      "deviceId": "ESP32-TEST-2",
      "gatewayId": "GW01",
      "name": "NODE_TEST2",
      "location": "indefinido",
      "status": "offline",
      "seq": 437,
      "rssi": -41,
      "battery": 3.88,
      "lastSeen": "2026-04-28T14:46:31.046Z",
      "samplingIntervalSec": 300
    },
    {
      "nodeId": "NODE_TEST4",
      "deviceId": "ESP32-TEST-4",
      "gatewayId": "GW01",
      "name": "NODE_TEST4",
      "location": "indefinido",
      "status": "offline",
      "seq": 383,
      "rssi": -39,
      "battery": 3.87,
      "lastSeen": "2026-04-28T14:46:46.098Z",
      "samplingIntervalSec": 300
    }
  ],
  "telemetry": [
    {
      "deviceId": "ESP32-004",
      "nodeId": "NODE10",
      "gatewayId": "GW01",
      "ts": "2026-05-13T08:28:04.040Z",
      "seq": 18065,
      "rssi": -89,
      "battery": 3.83,
      "sensors": {
        "bmp280": {
          "temperature_c": 28.2,
          "pressure_hpa": 1013.9
        },
        "mq7": {
          "gas_raw": 107,
          "co_ppm": 107.4
        },
        "ds18b20": {
          "temperature_c": 28.1
        }
      },
      "actuators": {
        "rgb_led": {
          "state": "off",
          "color": "off"
        }
      }
    },
    {
      "deviceId": "ESP32-004",
      "nodeId": "NODE10",
      "gatewayId": "GW01",
      "ts": "2026-05-13T08:28:09.054Z",
      "seq": 18066,
      "rssi": -91,
      "battery": 3.83,
      "sensors": {
        "bmp280": {
          "temperature_c": 27.4,
          "pressure_hpa": 1013.8
        },
        "mq7": {
          "gas_raw": 113,
          "co_ppm": 110.7
        },
        "ds18b20": {
          "temperature_c": 27.1
        }
      },
      "actuators": {
        "rgb_led": {
          "state": "on",
          "color": "green"
        }
      }
    },
    {
      "deviceId": "ESP32-004",
      "nodeId": "NODE10",
      "gatewayId": "GW01",
      "ts": "2026-05-13T08:28:14.054Z",
      "seq": 18067,
      "rssi": -90,
      "battery": 3.83,
      "sensors": {
        "bmp280": {
          "temperature_c": 28,
          "pressure_hpa": 1013.7
        },
        "mq7": {
          "gas_raw": 120,
          "co_ppm": 117.4
        },
        "ds18b20": {
          "temperature_c": 27.9
        }
      },
      "actuators": {
        "rgb_led": {
          "state": "on",
          "color": "blue"
        }
      }
    },
    {
      "deviceId": "ESP32-004",
      "nodeId": "NODE10",
      "gatewayId": "GW01",
      "ts": "2026-05-13T08:28:19.062Z",
      "seq": 18068,
      "rssi": -91,
      "battery": 3.83,
      "sensors": {
        "bmp280": {
          "temperature_c": 28.2,
          "pressure_hpa": 1012.2
        },
        "mq7": {
          "gas_raw": 117,
          "co_ppm": 120.4
        },
        "ds18b20": {
          "temperature_c": 28
        }
      },
      "actuators": {
        "rgb_led": {
          "state": "on",
          "color": "red"
        }
      }
    },
    {
      "deviceId": "ESP32-004",
      "nodeId": "NODE10",
      "gatewayId": "GW01",
      "ts": "2026-05-13T08:28:24.077Z",
      "seq": 18069,
      "rssi": -91,
      "battery": 3.83,
      "sensors": {
        "bmp280": {
          "temperature_c": 28.2,
          "pressure_hpa": 1012
        },
        "mq7": {
          "gas_raw": 133,
          "co_ppm": 137
        },
        "ds18b20": {
          "temperature_c": 28.1
        }
      },
      "actuators": {
        "rgb_led": {
          "state": "off",
          "color": "off"
        }
      }
    },
    {
      "deviceId": "ESP32-004",
      "nodeId": "NODE10",
      "gatewayId": "GW01",
      "ts": "2026-05-13T08:28:29.079Z",
      "seq": 18070,
      "rssi": -93,
      "battery": 3.83,
      "sensors": {
        "bmp280": {
          "temperature_c": 27.4,
          "pressure_hpa": 1012.8
        },
        "mq7": {
          "gas_raw": 130,
          "co_ppm": 126.6
        },
        "ds18b20": {
          "temperature_c": 27.3
        }
      },
      "actuators": {
        "rgb_led": {
          "state": "on",
          "color": "green"
        }
      }
    },
    {
      "deviceId": "ESP32-004",
      "nodeId": "NODE10",
      "gatewayId": "GW01",
      "ts": "2026-05-13T08:28:34.084Z",
      "seq": 18071,
      "rssi": -95,
      "battery": 3.83,
      "sensors": {
        "bmp280": {
          "temperature_c": 27.5,
          "pressure_hpa": 1012.3
        },
        "mq7": {
          "gas_raw": 127,
          "co_ppm": 128.1
        },
        "ds18b20": {
          "temperature_c": 27.4
        }
      },
      "actuators": {
        "rgb_led": {
          "state": "on",
          "color": "blue"
        }
      }
    },
    {
      "deviceId": "ESP32-004",
      "nodeId": "NODE10",
      "gatewayId": "GW01",
      "ts": "2026-05-13T08:28:39.088Z",
      "seq": 18072,
      "rssi": -95,
      "battery": 3.83,
      "sensors": {
        "bmp280": {
          "temperature_c": 27.9,
          "pressure_hpa": 1012.3
        },
        "mq7": {
          "gas_raw": 120,
          "co_ppm": 116.3
        },
        "ds18b20": {
          "temperature_c": 27.6
        }
      },
      "actuators": {
        "rgb_led": {
          "state": "on",
          "color": "red"
        }
      }
    },
    {
      "deviceId": "ESP32-004",
      "nodeId": "NODE10",
      "gatewayId": "GW01",
      "ts": "2026-05-13T08:28:44.093Z",
      "seq": 18073,
      "rssi": -94,
      "battery": 3.83,
      "sensors": {
        "bmp280": {
          "temperature_c": 28.8,
          "pressure_hpa": 1013.7
        },
        "mq7": {
          "gas_raw": 114,
          "co_ppm": 114.1
        },
        "ds18b20": {
          "temperature_c": 28.7
        }
      },
      "actuators": {
        "rgb_led": {
          "state": "off",
          "color": "off"
        }
      }
    },
    {
      "deviceId": "ESP32-004",
      "nodeId": "NODE10",
      "gatewayId": "GW01",
      "ts": "2026-05-13T08:28:49.099Z",
      "seq": 18074,
      "rssi": -95,
      "battery": 3.83,
      "sensors": {
        "bmp280": {
          "temperature_c": 27.3,
          "pressure_hpa": 1013.6
        },
        "mq7": {
          "gas_raw": 132,
          "co_ppm": 134.3
        },
        "ds18b20": {
          "temperature_c": 27.1
        }
      },
      "actuators": {
        "rgb_led": {
          "state": "on",
          "color": "green"
        }
      }
    },
    {
      "deviceId": "ESP32-004",
      "nodeId": "NODE10",
      "gatewayId": "GW01",
      "ts": "2026-05-13T08:28:54.108Z",
      "seq": 18075,
      "rssi": -94,
      "battery": 3.83,
      "sensors": {
        "bmp280": {
          "temperature_c": 28,
          "pressure_hpa": 1013.5
        },
        "mq7": {
          "gas_raw": 129,
          "co_ppm": 131.4
        },
        "ds18b20": {
          "temperature_c": 28
        }
      },
      "actuators": {
        "rgb_led": {
          "state": "on",
          "color": "blue"
        }
      }
    },
    {
      "deviceId": "ESP32-004",
      "nodeId": "NODE10",
      "gatewayId": "GW01",
      "ts": "2026-05-13T08:28:59.122Z",
      "seq": 18076,
      "rssi": -95,
      "battery": 3.83,
      "sensors": {
        "bmp280": {
          "temperature_c": 27.3,
          "pressure_hpa": 1012.6
        },
        "mq7": {
          "gas_raw": 133,
          "co_ppm": 132.9
        },
        "ds18b20": {
          "temperature_c": 27
        }
      },
      "actuators": {
        "rgb_led": {
          "state": "on",
          "color": "red"
        }
      }
    },
    {
      "deviceId": "ESP32-004",
      "nodeId": "NODE10",
      "gatewayId": "GW01",
      "ts": "2026-05-13T08:29:04.137Z",
      "seq": 18077,
      "rssi": -95,
      "battery": 3.83,
      "sensors": {
        "bmp280": {
          "temperature_c": 28.3,
          "pressure_hpa": 1012.9
        },
        "mq7": {
          "gas_raw": 123,
          "co_ppm": 126.2
        },
        "ds18b20": {
          "temperature_c": 28
        }
      },
      "actuators": {
        "rgb_led": {
          "state": "off",
          "color": "off"
        }
      }
    },
    {
      "deviceId": "ESP32-004",
      "nodeId": "NODE10",
      "gatewayId": "GW01",
      "ts": "2026-05-13T08:29:09.139Z",
      "seq": 18078,
      "rssi": -93,
      "battery": 3.83,
      "sensors": {
        "bmp280": {
          "temperature_c": 28.7,
          "pressure_hpa": 1012
        },
        "mq7": {
          "gas_raw": 113,
          "co_ppm": 110.7
        },
        "ds18b20": {
          "temperature_c": 28.7
        }
      },
      "actuators": {
        "rgb_led": {
          "state": "on",
          "color": "green"
        }
      }
    },
    {
      "deviceId": "ESP32-004",
      "nodeId": "NODE10",
      "gatewayId": "GW01",
      "ts": "2026-05-13T08:29:14.141Z",
      "seq": 18079,
      "rssi": -94,
      "battery": 3.83,
      "sensors": {
        "bmp280": {
          "temperature_c": 28.7,
          "pressure_hpa": 1013
        },
        "mq7": {
          "gas_raw": 128,
          "co_ppm": 128.1
        },
        "ds18b20": {
          "temperature_c": 28.5
        }
      },
      "actuators": {
        "rgb_led": {
          "state": "on",
          "color": "blue"
        }
      }
    },
    {
      "deviceId": "ESP32-004",
      "nodeId": "NODE10",
      "gatewayId": "GW01",
      "ts": "2026-05-13T08:29:19.145Z",
      "seq": 18080,
      "rssi": -92,
      "battery": 3.83,
      "sensors": {
        "bmp280": {
          "temperature_c": 28.8,
          "pressure_hpa": 1013.6
        },
        "mq7": {
          "gas_raw": 131,
          "co_ppm": 129.2
        },
        "ds18b20": {
          "temperature_c": 29
        }
      },
      "actuators": {
        "rgb_led": {
          "state": "on",
          "color": "red"
        }
      }
    },
    {
      "deviceId": "ESP32-004",
      "nodeId": "NODE10",
      "gatewayId": "GW01",
      "ts": "2026-05-13T08:29:24.149Z",
      "seq": 18081,
      "rssi": -91,
      "battery": 3.83,
      "sensors": {
        "bmp280": {
          "temperature_c": 28.9,
          "pressure_hpa": 1012.3
        },
        "mq7": {
          "gas_raw": 116,
          "co_ppm": 118
        },
        "ds18b20": {
          "temperature_c": 28.9
        }
      },
      "actuators": {
        "rgb_led": {
          "state": "off",
          "color": "off"
        }
      }
    },
    {
      "deviceId": "ESP32-004",
      "nodeId": "NODE10",
      "gatewayId": "GW01",
      "ts": "2026-05-13T08:29:29.155Z",
      "seq": 18082,
      "rssi": -90,
      "battery": 3.83,
      "sensors": {
        "bmp280": {
          "temperature_c": 29,
          "pressure_hpa": 1011.9
        },
        "mq7": {
          "gas_raw": 133,
          "co_ppm": 136.5
        },
        "ds18b20": {
          "temperature_c": 29
        }
      },
      "actuators": {
        "rgb_led": {
          "state": "on",
          "color": "green"
        }
      }
    },
    {
      "deviceId": "ESP32-004",
      "nodeId": "NODE10",
      "gatewayId": "GW01",
      "ts": "2026-05-13T08:29:34.168Z",
      "seq": 18083,
      "rssi": -92,
      "battery": 3.83,
      "sensors": {
        "bmp280": {
          "temperature_c": 28.8,
          "pressure_hpa": 1012.4
        },
        "mq7": {
          "gas_raw": 109,
          "co_ppm": 109.8
        },
        "ds18b20": {
          "temperature_c": 28.6
        }
      },
      "actuators": {
        "rgb_led": {
          "state": "on",
          "color": "blue"
        }
      }
    },
    {
      "deviceId": "ESP32-004",
      "nodeId": "NODE10",
      "gatewayId": "GW01",
      "ts": "2026-05-13T08:29:39.169Z",
      "seq": 18084,
      "rssi": -90,
      "battery": 3.83,
      "sensors": {
        "bmp280": {
          "temperature_c": 27.9,
          "pressure_hpa": 1012.6
        },
        "mq7": {
          "gas_raw": 133,
          "co_ppm": 136.6
        },
        "ds18b20": {
          "temperature_c": 27.8
        }
      },
      "actuators": {
        "rgb_led": {
          "state": "on",
          "color": "red"
        }
      }
    },
    {
      "deviceId": "ESP32-004",
      "nodeId": "NODE10",
      "gatewayId": "GW01",
      "ts": "2026-05-13T08:29:44.172Z",
      "seq": 18085,
      "rssi": -92,
      "battery": 3.83,
      "sensors": {
        "bmp280": {
          "temperature_c": 28.9,
          "pressure_hpa": 1012.9
        },
        "mq7": {
          "gas_raw": 105,
          "co_ppm": 104.8
        },
        "ds18b20": {
          "temperature_c": 29
        }
      },
      "actuators": {
        "rgb_led": {
          "state": "off",
          "color": "off"
        }
      }
    },
    {
      "deviceId": "ESP32-004",
      "nodeId": "NODE10",
      "gatewayId": "GW01",
      "ts": "2026-05-13T08:29:49.176Z",
      "seq": 18086,
      "rssi": -94,
      "battery": 3.83,
      "sensors": {
        "bmp280": {
          "temperature_c": 27.3,
          "pressure_hpa": 1013.5
        },
        "mq7": {
          "gas_raw": 108,
          "co_ppm": 110.3
        },
        "ds18b20": {
          "temperature_c": 27.2
        }
      },
      "actuators": {
        "rgb_led": {
          "state": "on",
          "color": "green"
        }
      }
    },
    {
      "deviceId": "ESP32-004",
      "nodeId": "NODE10",
      "gatewayId": "GW01",
      "ts": "2026-05-13T08:29:54.191Z",
      "seq": 18087,
      "rssi": -93,
      "battery": 3.83,
      "sensors": {
        "bmp280": {
          "temperature_c": 29,
          "pressure_hpa": 1013.3
        },
        "mq7": {
          "gas_raw": 124,
          "co_ppm": 126.1
        },
        "ds18b20": {
          "temperature_c": 29.2
        }
      },
      "actuators": {
        "rgb_led": {
          "state": "on",
          "color": "blue"
        }
      }
    },
    {
      "deviceId": "ESP32-004",
      "nodeId": "NODE10",
      "gatewayId": "GW01",
      "ts": "2026-05-13T08:29:59.206Z",
      "seq": 18088,
      "rssi": -93,
      "battery": 3.83,
      "sensors": {
        "bmp280": {
          "temperature_c": 27.4,
          "pressure_hpa": 1013.4
        },
        "mq7": {
          "gas_raw": 117,
          "co_ppm": 117.1
        },
        "ds18b20": {
          "temperature_c": 27.4
        }
      },
      "actuators": {
        "rgb_led": {
          "state": "on",
          "color": "red"
        }
      }
    },
    {
      "deviceId": "ESP32-004",
      "nodeId": "NODE10",
      "gatewayId": "GW01",
      "ts": "2026-05-13T08:30:04.212Z",
      "seq": 18089,
      "rssi": -91,
      "battery": 3.83,
      "sensors": {
        "bmp280": {
          "temperature_c": 29,
          "pressure_hpa": 1013.3
        },
        "mq7": {
          "gas_raw": 129,
          "co_ppm": 127.5
        },
        "ds18b20": {
          "temperature_c": 29
        }
      },
      "actuators": {
        "rgb_led": {
          "state": "off",
          "color": "off"
        }
      }
    },
    {
      "deviceId": "ESP32-004",
      "nodeId": "NODE10",
      "gatewayId": "GW01",
      "ts": "2026-05-13T08:30:09.222Z",
      "seq": 18090,
      "rssi": -92,
      "battery": 3.83,
      "sensors": {
        "bmp280": {
          "temperature_c": 28.4,
          "pressure_hpa": 1012.8
        },
        "mq7": {
          "gas_raw": 113,
          "co_ppm": 111.1
        },
        "ds18b20": {
          "temperature_c": 28.2
        }
      },
      "actuators": {
        "rgb_led": {
          "state": "on",
          "color": "green"
        }
      }
    },
    {
      "deviceId": "ESP32-004",
      "nodeId": "NODE10",
      "gatewayId": "GW01",
      "ts": "2026-05-13T08:30:14.236Z",
      "seq": 18091,
      "rssi": -92,
      "battery": 3.83,
      "sensors": {
        "bmp280": {
          "temperature_c": 28.3,
          "pressure_hpa": 1013.2
        },
        "mq7": {
          "gas_raw": 118,
          "co_ppm": 119.8
        },
        "ds18b20": {
          "temperature_c": 28.1
        }
      },
      "actuators": {
        "rgb_led": {
          "state": "on",
          "color": "blue"
        }
      }
    },
    {
      "deviceId": "ESP32-004",
      "nodeId": "NODE10",
      "gatewayId": "GW01",
      "ts": "2026-05-13T08:30:19.250Z",
      "seq": 18092,
      "rssi": -92,
      "battery": 3.83,
      "sensors": {
        "bmp280": {
          "temperature_c": 27.3,
          "pressure_hpa": 1014.2
        },
        "mq7": {
          "gas_raw": 118,
          "co_ppm": 115.9
        },
        "ds18b20": {
          "temperature_c": 27.5
        }
      },
      "actuators": {
        "rgb_led": {
          "state": "on",
          "color": "red"
        }
      }
    },
    {
      "deviceId": "ESP32-004",
      "nodeId": "NODE10",
      "gatewayId": "GW01",
      "ts": "2026-05-13T08:30:24.264Z",
      "seq": 18093,
      "rssi": -91,
      "battery": 3.83,
      "sensors": {
        "bmp280": {
          "temperature_c": 28.4,
          "pressure_hpa": 1013.5
        },
        "mq7": {
          "gas_raw": 105,
          "co_ppm": 108.4
        },
        "ds18b20": {
          "temperature_c": 28.6
        }
      },
      "actuators": {
        "rgb_led": {
          "state": "off",
          "color": "off"
        }
      }
    },
    {
      "deviceId": "ESP32-004",
      "nodeId": "NODE10",
      "gatewayId": "GW01",
      "ts": "2026-05-13T08:30:29.272Z",
      "seq": 18094,
      "rssi": -91,
      "battery": 3.83,
      "sensors": {
        "bmp280": {
          "temperature_c": 27.7,
          "pressure_hpa": 1012.1
        },
        "mq7": {
          "gas_raw": 128,
          "co_ppm": 128.6
        },
        "ds18b20": {
          "temperature_c": 27.5
        }
      },
      "actuators": {
        "rgb_led": {
          "state": "on",
          "color": "green"
        }
      }
    },
    {
      "deviceId": "ESP32-004",
      "nodeId": "NODE10",
      "gatewayId": "GW01",
      "ts": "2026-05-13T08:30:34.272Z",
      "seq": 18095,
      "rssi": -92,
      "battery": 3.83,
      "sensors": {
        "bmp280": {
          "temperature_c": 28.4,
          "pressure_hpa": 1011.9
        },
        "mq7": {
          "gas_raw": 128,
          "co_ppm": 128.9
        },
        "ds18b20": {
          "temperature_c": 28.2
        }
      },
      "actuators": {
        "rgb_led": {
          "state": "on",
          "color": "blue"
        }
      }
    },
    {
      "deviceId": "ESP32-004",
      "nodeId": "NODE10",
      "gatewayId": "GW01",
      "ts": "2026-05-13T08:30:39.277Z",
      "seq": 18096,
      "rssi": -93,
      "battery": 3.83,
      "sensors": {
        "bmp280": {
          "temperature_c": 27.6,
          "pressure_hpa": 1012.2
        },
        "mq7": {
          "gas_raw": 108,
          "co_ppm": 111.7
        },
        "ds18b20": {
          "temperature_c": 27.4
        }
      },
      "actuators": {
        "rgb_led": {
          "state": "on",
          "color": "red"
        }
      }
    },
    {
      "deviceId": "ESP32-004",
      "nodeId": "NODE10",
      "gatewayId": "GW01",
      "ts": "2026-05-13T08:30:44.284Z",
      "seq": 18097,
      "rssi": -94,
      "battery": 3.83,
      "sensors": {
        "bmp280": {
          "temperature_c": 27.3,
          "pressure_hpa": 1014.1
        },
        "mq7": {
          "gas_raw": 128,
          "co_ppm": 129
        },
        "ds18b20": {
          "temperature_c": 27.1
        }
      },
      "actuators": {
        "rgb_led": {
          "state": "off",
          "color": "off"
        }
      }
    },
    {
      "deviceId": "ESP32-004",
      "nodeId": "NODE10",
      "gatewayId": "GW01",
      "ts": "2026-05-13T08:30:49.284Z",
      "seq": 18098,
      "rssi": -94,
      "battery": 3.83,
      "sensors": {
        "bmp280": {
          "temperature_c": 28.4,
          "pressure_hpa": 1013.8
        },
        "mq7": {
          "gas_raw": 112,
          "co_ppm": 108.8
        },
        "ds18b20": {
          "temperature_c": 28.3
        }
      },
      "actuators": {
        "rgb_led": {
          "state": "on",
          "color": "green"
        }
      }
    },
    {
      "deviceId": "ESP32-004",
      "nodeId": "NODE10",
      "gatewayId": "GW01",
      "ts": "2026-05-13T08:30:54.286Z",
      "seq": 18099,
      "rssi": -95,
      "battery": 3.83,
      "sensors": {
        "bmp280": {
          "temperature_c": 28.3,
          "pressure_hpa": 1012.4
        },
        "mq7": {
          "gas_raw": 129,
          "co_ppm": 128.2
        },
        "ds18b20": {
          "temperature_c": 28.1
        }
      },
      "actuators": {
        "rgb_led": {
          "state": "on",
          "color": "blue"
        }
      }
    },
    {
      "deviceId": "ESP32-004",
      "nodeId": "NODE10",
      "gatewayId": "GW01",
      "ts": "2026-05-13T08:30:59.291Z",
      "seq": 18100,
      "rssi": -95,
      "battery": 3.83,
      "sensors": {
        "bmp280": {
          "temperature_c": 28.7,
          "pressure_hpa": 1012.3
        },
        "mq7": {
          "gas_raw": 104,
          "co_ppm": 104.6
        },
        "ds18b20": {
          "temperature_c": 28.6
        }
      },
      "actuators": {
        "rgb_led": {
          "state": "on",
          "color": "red"
        }
      }
    },
    {
      "deviceId": "ESP32-004",
      "nodeId": "NODE10",
      "gatewayId": "GW01",
      "ts": "2026-05-13T08:31:04.301Z",
      "seq": 18101,
      "rssi": -95,
      "battery": 3.83,
      "sensors": {
        "bmp280": {
          "temperature_c": 28.2,
          "pressure_hpa": 1012.6
        },
        "mq7": {
          "gas_raw": 114,
          "co_ppm": 115.5
        },
        "ds18b20": {
          "temperature_c": 28
        }
      },
      "actuators": {
        "rgb_led": {
          "state": "off",
          "color": "off"
        }
      }
    },
    {
      "deviceId": "ESP32-004",
      "nodeId": "NODE10",
      "gatewayId": "GW01",
      "ts": "2026-05-13T08:31:09.302Z",
      "seq": 18102,
      "rssi": -95,
      "battery": 3.83,
      "sensors": {
        "bmp280": {
          "temperature_c": 28.1,
          "pressure_hpa": 1013.3
        },
        "mq7": {
          "gas_raw": 121,
          "co_ppm": 124.9
        },
        "ds18b20": {
          "temperature_c": 28.1
        }
      },
      "actuators": {
        "rgb_led": {
          "state": "on",
          "color": "green"
        }
      }
    },
    {
      "deviceId": "ESP32-004",
      "nodeId": "NODE10",
      "gatewayId": "GW01",
      "ts": "2026-05-13T08:31:14.312Z",
      "seq": 18103,
      "rssi": -95,
      "battery": 3.83,
      "sensors": {
        "bmp280": {
          "temperature_c": 28.4,
          "pressure_hpa": 1012
        },
        "mq7": {
          "gas_raw": 118,
          "co_ppm": 120
        },
        "ds18b20": {
          "temperature_c": 28.3
        }
      },
      "actuators": {
        "rgb_led": {
          "state": "on",
          "color": "blue"
        }
      }
    },
    {
      "deviceId": "ESP32-004",
      "nodeId": "NODE10",
      "gatewayId": "GW01",
      "ts": "2026-05-13T08:31:19.322Z",
      "seq": 18104,
      "rssi": -95,
      "battery": 3.83,
      "sensors": {
        "bmp280": {
          "temperature_c": 28.6,
          "pressure_hpa": 1012.2
        },
        "mq7": {
          "gas_raw": 113,
          "co_ppm": 115
        },
        "ds18b20": {
          "temperature_c": 28.4
        }
      },
      "actuators": {
        "rgb_led": {
          "state": "on",
          "color": "red"
        }
      }
    },
    {
      "deviceId": "ESP32-004",
      "nodeId": "NODE10",
      "gatewayId": "GW01",
      "ts": "2026-05-13T08:31:24.327Z",
      "seq": 18105,
      "rssi": -93,
      "battery": 3.83,
      "sensors": {
        "bmp280": {
          "temperature_c": 27.6,
          "pressure_hpa": 1014.1
        },
        "mq7": {
          "gas_raw": 105,
          "co_ppm": 105
        },
        "ds18b20": {
          "temperature_c": 27.8
        }
      },
      "actuators": {
        "rgb_led": {
          "state": "off",
          "color": "off"
        }
      }
    },
    {
      "deviceId": "ESP32-004",
      "nodeId": "NODE10",
      "gatewayId": "GW01",
      "ts": "2026-05-13T08:31:29.327Z",
      "seq": 18106,
      "rssi": -94,
      "battery": 3.83,
      "sensors": {
        "bmp280": {
          "temperature_c": 28.3,
          "pressure_hpa": 1012.3
        },
        "mq7": {
          "gas_raw": 135,
          "co_ppm": 131.5
        },
        "ds18b20": {
          "temperature_c": 28.4
        }
      },
      "actuators": {
        "rgb_led": {
          "state": "on",
          "color": "green"
        }
      }
    },
    {
      "deviceId": "ESP32-004",
      "nodeId": "NODE10",
      "gatewayId": "GW01",
      "ts": "2026-05-13T08:31:34.340Z",
      "seq": 18107,
      "rssi": -95,
      "battery": 3.83,
      "sensors": {
        "bmp280": {
          "temperature_c": 27.8,
          "pressure_hpa": 1012.6
        },
        "mq7": {
          "gas_raw": 136,
          "co_ppm": 136.1
        },
        "ds18b20": {
          "temperature_c": 28
        }
      },
      "actuators": {
        "rgb_led": {
          "state": "on",
          "color": "blue"
        }
      }
    },
    {
      "deviceId": "ESP32-004",
      "nodeId": "NODE10",
      "gatewayId": "GW01",
      "ts": "2026-05-13T08:31:39.347Z",
      "seq": 18108,
      "rssi": -93,
      "battery": 3.83,
      "sensors": {
        "bmp280": {
          "temperature_c": 28.6,
          "pressure_hpa": 1012.3
        },
        "mq7": {
          "gas_raw": 125,
          "co_ppm": 121.7
        },
        "ds18b20": {
          "temperature_c": 28.4
        }
      },
      "actuators": {
        "rgb_led": {
          "state": "on",
          "color": "red"
        }
      }
    },
    {
      "deviceId": "ESP32-004",
      "nodeId": "NODE10",
      "gatewayId": "GW01",
      "ts": "2026-05-13T08:31:44.353Z",
      "seq": 18109,
      "rssi": -91,
      "battery": 3.83,
      "sensors": {
        "bmp280": {
          "temperature_c": 27.5,
          "pressure_hpa": 1014.1
        },
        "mq7": {
          "gas_raw": 112,
          "co_ppm": 109.3
        },
        "ds18b20": {
          "temperature_c": 27.7
        }
      },
      "actuators": {
        "rgb_led": {
          "state": "off",
          "color": "off"
        }
      }
    },
    {
      "deviceId": "ESP32-004",
      "nodeId": "NODE10",
      "gatewayId": "GW01",
      "ts": "2026-05-13T08:31:49.356Z",
      "seq": 18110,
      "rssi": -92,
      "battery": 3.83,
      "sensors": {
        "bmp280": {
          "temperature_c": 28.6,
          "pressure_hpa": 1012.5
        },
        "mq7": {
          "gas_raw": 132,
          "co_ppm": 132.3
        },
        "ds18b20": {
          "temperature_c": 28.6
        }
      },
      "actuators": {
        "rgb_led": {
          "state": "on",
          "color": "green"
        }
      }
    },
    {
      "deviceId": "ESP32-004",
      "nodeId": "NODE10",
      "gatewayId": "GW01",
      "ts": "2026-05-13T08:31:54.368Z",
      "seq": 18111,
      "rssi": -91,
      "battery": 3.83,
      "sensors": {
        "bmp280": {
          "temperature_c": 27.4,
          "pressure_hpa": 1012.8
        },
        "mq7": {
          "gas_raw": 108,
          "co_ppm": 109.1
        },
        "ds18b20": {
          "temperature_c": 27.5
        }
      },
      "actuators": {
        "rgb_led": {
          "state": "on",
          "color": "blue"
        }
      }
    },
    {
      "deviceId": "ESP32-004",
      "nodeId": "NODE10",
      "gatewayId": "GW01",
      "ts": "2026-05-13T08:31:59.378Z",
      "seq": 18112,
      "rssi": -90,
      "battery": 3.83,
      "sensors": {
        "bmp280": {
          "temperature_c": 28.5,
          "pressure_hpa": 1012.4
        },
        "mq7": {
          "gas_raw": 121,
          "co_ppm": 119.9
        },
        "ds18b20": {
          "temperature_c": 28.6
        }
      },
      "actuators": {
        "rgb_led": {
          "state": "on",
          "color": "red"
        }
      }
    },
    {
      "deviceId": "ESP32-004",
      "nodeId": "NODE10",
      "gatewayId": "GW01",
      "ts": "2026-05-13T08:32:04.386Z",
      "seq": 18113,
      "rssi": -90,
      "battery": 3.83,
      "sensors": {
        "bmp280": {
          "temperature_c": 28.3,
          "pressure_hpa": 1013.6
        },
        "mq7": {
          "gas_raw": 107,
          "co_ppm": 103.6
        },
        "ds18b20": {
          "temperature_c": 28.1
        }
      },
      "actuators": {
        "rgb_led": {
          "state": "off",
          "color": "off"
        }
      }
    },
    {
      "deviceId": "ESP32-004",
      "nodeId": "NODE10",
      "gatewayId": "GW01",
      "ts": "2026-05-13T08:32:09.391Z",
      "seq": 18114,
      "rssi": -89,
      "battery": 3.83,
      "sensors": {
        "bmp280": {
          "temperature_c": 28,
          "pressure_hpa": 1014.1
        },
        "mq7": {
          "gas_raw": 119,
          "co_ppm": 117.3
        },
        "ds18b20": {
          "temperature_c": 28.1
        }
      },
      "actuators": {
        "rgb_led": {
          "state": "on",
          "color": "green"
        }
      }
    },
    {
      "deviceId": "ESP32-004",
      "nodeId": "NODE10",
      "gatewayId": "GW01",
      "ts": "2026-05-13T08:32:14.396Z",
      "seq": 18115,
      "rssi": -90,
      "battery": 3.83,
      "sensors": {
        "bmp280": {
          "temperature_c": 28.1,
          "pressure_hpa": 1012.9
        },
        "mq7": {
          "gas_raw": 104,
          "co_ppm": 107.8
        },
        "ds18b20": {
          "temperature_c": 27.9
        }
      },
      "actuators": {
        "rgb_led": {
          "state": "on",
          "color": "blue"
        }
      }
    },
    {
      "deviceId": "ESP32-004",
      "nodeId": "NODE10",
      "gatewayId": "GW01",
      "ts": "2026-05-13T08:32:19.403Z",
      "seq": 18116,
      "rssi": -90,
      "battery": 3.83,
      "sensors": {
        "bmp280": {
          "temperature_c": 28,
          "pressure_hpa": 1012.7
        },
        "mq7": {
          "gas_raw": 129,
          "co_ppm": 131.3
        },
        "ds18b20": {
          "temperature_c": 28.2
        }
      },
      "actuators": {
        "rgb_led": {
          "state": "on",
          "color": "red"
        }
      }
    },
    {
      "deviceId": "ESP32-004",
      "nodeId": "NODE10",
      "gatewayId": "GW01",
      "ts": "2026-05-13T08:32:24.412Z",
      "seq": 18117,
      "rssi": -90,
      "battery": 3.83,
      "sensors": {
        "bmp280": {
          "temperature_c": 27.8,
          "pressure_hpa": 1012.6
        },
        "mq7": {
          "gas_raw": 105,
          "co_ppm": 108.2
        },
        "ds18b20": {
          "temperature_c": 27.5
        }
      },
      "actuators": {
        "rgb_led": {
          "state": "off",
          "color": "off"
        }
      }
    },
    {
      "deviceId": "ESP32-004",
      "nodeId": "NODE10",
      "gatewayId": "GW01",
      "ts": "2026-05-13T08:32:29.414Z",
      "seq": 18118,
      "rssi": -90,
      "battery": 3.83,
      "sensors": {
        "bmp280": {
          "temperature_c": 27.9,
          "pressure_hpa": 1013
        },
        "mq7": {
          "gas_raw": 123,
          "co_ppm": 126.7
        },
        "ds18b20": {
          "temperature_c": 27.9
        }
      },
      "actuators": {
        "rgb_led": {
          "state": "on",
          "color": "green"
        }
      }
    },
    {
      "deviceId": "ESP32-004",
      "nodeId": "NODE10",
      "gatewayId": "GW01",
      "ts": "2026-05-13T08:32:34.420Z",
      "seq": 18119,
      "rssi": -91,
      "battery": 3.83,
      "sensors": {
        "bmp280": {
          "temperature_c": 28.1,
          "pressure_hpa": 1014.1
        },
        "mq7": {
          "gas_raw": 129,
          "co_ppm": 131.3
        },
        "ds18b20": {
          "temperature_c": 28.1
        }
      },
      "actuators": {
        "rgb_led": {
          "state": "on",
          "color": "blue"
        }
      }
    },
    {
      "deviceId": "ESP32-004",
      "nodeId": "NODE10",
      "gatewayId": "GW01",
      "ts": "2026-05-13T08:32:39.435Z",
      "seq": 18120,
      "rssi": -89,
      "battery": 3.83,
      "sensors": {
        "bmp280": {
          "temperature_c": 27.6,
          "pressure_hpa": 1013.9
        },
        "mq7": {
          "gas_raw": 115,
          "co_ppm": 112.5
        },
        "ds18b20": {
          "temperature_c": 27.3
        }
      },
      "actuators": {
        "rgb_led": {
          "state": "on",
          "color": "red"
        }
      }
    },
    {
      "deviceId": "ESP32-004",
      "nodeId": "NODE10",
      "gatewayId": "GW01",
      "ts": "2026-05-13T08:32:44.444Z",
      "seq": 18121,
      "rssi": -90,
      "battery": 3.83,
      "sensors": {
        "bmp280": {
          "temperature_c": 28.4,
          "pressure_hpa": 1011.9
        },
        "mq7": {
          "gas_raw": 130,
          "co_ppm": 129.3
        },
        "ds18b20": {
          "temperature_c": 28.4
        }
      },
      "actuators": {
        "rgb_led": {
          "state": "off",
          "color": "off"
        }
      }
    },
    {
      "deviceId": "ESP32-004",
      "nodeId": "NODE10",
      "gatewayId": "GW01",
      "ts": "2026-05-13T08:32:49.459Z",
      "seq": 18122,
      "rssi": -91,
      "battery": 3.83,
      "sensors": {
        "bmp280": {
          "temperature_c": 27.7,
          "pressure_hpa": 1013.2
        },
        "mq7": {
          "gas_raw": 111,
          "co_ppm": 110.1
        },
        "ds18b20": {
          "temperature_c": 27.9
        }
      },
      "actuators": {
        "rgb_led": {
          "state": "on",
          "color": "green"
        }
      }
    },
    {
      "deviceId": "ESP32-004",
      "nodeId": "NODE10",
      "gatewayId": "GW01",
      "ts": "2026-05-13T08:32:54.461Z",
      "seq": 18123,
      "rssi": -89,
      "battery": 3.83,
      "sensors": {
        "bmp280": {
          "temperature_c": 27.9,
          "pressure_hpa": 1011.9
        },
        "mq7": {
          "gas_raw": 106,
          "co_ppm": 108.3
        },
        "ds18b20": {
          "temperature_c": 28
        }
      },
      "actuators": {
        "rgb_led": {
          "state": "on",
          "color": "blue"
        }
      }
    },
    {
      "deviceId": "ESP32-004",
      "nodeId": "NODE10",
      "gatewayId": "GW01",
      "ts": "2026-05-13T08:32:59.475Z",
      "seq": 18124,
      "rssi": -90,
      "battery": 3.83,
      "sensors": {
        "bmp280": {
          "temperature_c": 27.3,
          "pressure_hpa": 1013.6
        },
        "mq7": {
          "gas_raw": 136,
          "co_ppm": 133.4
        },
        "ds18b20": {
          "temperature_c": 27
        }
      },
      "actuators": {
        "rgb_led": {
          "state": "on",
          "color": "red"
        }
      }
    },
    {
      "deviceId": "ESP32-004",
      "nodeId": "NODE10",
      "gatewayId": "GW01",
      "ts": "2026-05-13T08:33:04.490Z",
      "seq": 18125,
      "rssi": -89,
      "battery": 3.83,
      "sensors": {
        "bmp280": {
          "temperature_c": 27.2,
          "pressure_hpa": 1013.9
        },
        "mq7": {
          "gas_raw": 103,
          "co_ppm": 100.8
        },
        "ds18b20": {
          "temperature_c": 27
        }
      },
      "actuators": {
        "rgb_led": {
          "state": "off",
          "color": "off"
        }
      }
    },
    {
      "deviceId": "ESP32-004",
      "nodeId": "NODE10",
      "gatewayId": "GW01",
      "ts": "2026-05-13T08:33:09.498Z",
      "seq": 18126,
      "rssi": -88,
      "battery": 3.83,
      "sensors": {
        "bmp280": {
          "temperature_c": 27.9,
          "pressure_hpa": 1012.8
        },
        "mq7": {
          "gas_raw": 133,
          "co_ppm": 129.3
        },
        "ds18b20": {
          "temperature_c": 27.8
        }
      },
      "actuators": {
        "rgb_led": {
          "state": "on",
          "color": "green"
        }
      }
    },
    {
      "deviceId": "ESP32-004",
      "nodeId": "NODE10",
      "gatewayId": "GW01",
      "ts": "2026-05-13T08:33:14.509Z",
      "seq": 18127,
      "rssi": -90,
      "battery": 3.83,
      "sensors": {
        "bmp280": {
          "temperature_c": 28.5,
          "pressure_hpa": 1013.8
        },
        "mq7": {
          "gas_raw": 135,
          "co_ppm": 131.3
        },
        "ds18b20": {
          "temperature_c": 28.6
        }
      },
      "actuators": {
        "rgb_led": {
          "state": "on",
          "color": "blue"
        }
      }
    },
    {
      "deviceId": "ESP32-004",
      "nodeId": "NODE10",
      "gatewayId": "GW01",
      "ts": "2026-05-13T08:33:19.512Z",
      "seq": 18128,
      "rssi": -88,
      "battery": 3.83,
      "sensors": {
        "bmp280": {
          "temperature_c": 27.5,
          "pressure_hpa": 1014
        },
        "mq7": {
          "gas_raw": 131,
          "co_ppm": 130.1
        },
        "ds18b20": {
          "temperature_c": 27.3
        }
      },
      "actuators": {
        "rgb_led": {
          "state": "on",
          "color": "red"
        }
      }
    },
    {
      "deviceId": "ESP32-004",
      "nodeId": "NODE10",
      "gatewayId": "GW01",
      "ts": "2026-05-13T08:33:24.527Z",
      "seq": 18129,
      "rssi": -88,
      "battery": 3.83,
      "sensors": {
        "bmp280": {
          "temperature_c": 28.9,
          "pressure_hpa": 1013.3
        },
        "mq7": {
          "gas_raw": 110,
          "co_ppm": 108.8
        },
        "ds18b20": {
          "temperature_c": 28.8
        }
      },
      "actuators": {
        "rgb_led": {
          "state": "off",
          "color": "off"
        }
      }
    },
    {
      "deviceId": "ESP32-004",
      "nodeId": "NODE10",
      "gatewayId": "GW01",
      "ts": "2026-05-13T08:33:29.542Z",
      "seq": 18130,
      "rssi": -86,
      "battery": 3.83,
      "sensors": {
        "bmp280": {
          "temperature_c": 27.8,
          "pressure_hpa": 1012.6
        },
        "mq7": {
          "gas_raw": 111,
          "co_ppm": 109.3
        },
        "ds18b20": {
          "temperature_c": 27.6
        }
      },
      "actuators": {
        "rgb_led": {
          "state": "on",
          "color": "green"
        }
      }
    },
    {
      "deviceId": "ESP32-004",
      "nodeId": "NODE10",
      "gatewayId": "GW01",
      "ts": "2026-05-13T08:33:34.547Z",
      "seq": 18131,
      "rssi": -85,
      "battery": 3.83,
      "sensors": {
        "bmp280": {
          "temperature_c": 28.6,
          "pressure_hpa": 1013.9
        },
        "mq7": {
          "gas_raw": 107,
          "co_ppm": 109.8
        },
        "ds18b20": {
          "temperature_c": 28.8
        }
      },
      "actuators": {
        "rgb_led": {
          "state": "on",
          "color": "blue"
        }
      }
    },
    {
      "deviceId": "ESP32-004",
      "nodeId": "NODE10",
      "gatewayId": "GW01",
      "ts": "2026-05-13T08:33:39.547Z",
      "seq": 18132,
      "rssi": -84,
      "battery": 3.83,
      "sensors": {
        "bmp280": {
          "temperature_c": 27.5,
          "pressure_hpa": 1012.1
        },
        "mq7": {
          "gas_raw": 113,
          "co_ppm": 113.6
        },
        "ds18b20": {
          "temperature_c": 27.2
        }
      },
      "actuators": {
        "rgb_led": {
          "state": "on",
          "color": "red"
        }
      }
    },
    {
      "deviceId": "ESP32-004",
      "nodeId": "NODE10",
      "gatewayId": "GW01",
      "ts": "2026-05-13T08:33:44.549Z",
      "seq": 18133,
      "rssi": -84,
      "battery": 3.83,
      "sensors": {
        "bmp280": {
          "temperature_c": 28.5,
          "pressure_hpa": 1011.9
        },
        "mq7": {
          "gas_raw": 116,
          "co_ppm": 114.2
        },
        "ds18b20": {
          "temperature_c": 28.7
        }
      },
      "actuators": {
        "rgb_led": {
          "state": "off",
          "color": "off"
        }
      }
    },
    {
      "deviceId": "ESP32-004",
      "nodeId": "NODE10",
      "gatewayId": "GW01",
      "ts": "2026-05-13T08:33:49.549Z",
      "seq": 18134,
      "rssi": -85,
      "battery": 3.83,
      "sensors": {
        "bmp280": {
          "temperature_c": 28.4,
          "pressure_hpa": 1014.1
        },
        "mq7": {
          "gas_raw": 109,
          "co_ppm": 107.2
        },
        "ds18b20": {
          "temperature_c": 28.6
        }
      },
      "actuators": {
        "rgb_led": {
          "state": "on",
          "color": "green"
        }
      }
    },
    {
      "deviceId": "ESP32-004",
      "nodeId": "NODE10",
      "gatewayId": "GW01",
      "ts": "2026-05-13T08:33:54.560Z",
      "seq": 18135,
      "rssi": -86,
      "battery": 3.83,
      "sensors": {
        "bmp280": {
          "temperature_c": 27.6,
          "pressure_hpa": 1014
        },
        "mq7": {
          "gas_raw": 133,
          "co_ppm": 137
        },
        "ds18b20": {
          "temperature_c": 27.4
        }
      },
      "actuators": {
        "rgb_led": {
          "state": "on",
          "color": "blue"
        }
      }
    },
    {
      "deviceId": "ESP32-004",
      "nodeId": "NODE10",
      "gatewayId": "GW01",
      "ts": "2026-05-13T08:33:59.573Z",
      "seq": 18136,
      "rssi": -84,
      "battery": 3.83,
      "sensors": {
        "bmp280": {
          "temperature_c": 27.3,
          "pressure_hpa": 1013
        },
        "mq7": {
          "gas_raw": 119,
          "co_ppm": 116.3
        },
        "ds18b20": {
          "temperature_c": 27.2
        }
      },
      "actuators": {
        "rgb_led": {
          "state": "on",
          "color": "red"
        }
      }
    },
    {
      "deviceId": "ESP32-004",
      "nodeId": "NODE10",
      "gatewayId": "GW01",
      "ts": "2026-05-13T08:34:04.575Z",
      "seq": 18137,
      "rssi": -83,
      "battery": 3.83,
      "sensors": {
        "bmp280": {
          "temperature_c": 28.8,
          "pressure_hpa": 1013.5
        },
        "mq7": {
          "gas_raw": 131,
          "co_ppm": 130.3
        },
        "ds18b20": {
          "temperature_c": 28.7
        }
      },
      "actuators": {
        "rgb_led": {
          "state": "off",
          "color": "off"
        }
      }
    },
    {
      "deviceId": "ESP32-004",
      "nodeId": "NODE10",
      "gatewayId": "GW01",
      "ts": "2026-05-13T08:34:09.581Z",
      "seq": 18138,
      "rssi": -83,
      "battery": 3.83,
      "sensors": {
        "bmp280": {
          "temperature_c": 28.6,
          "pressure_hpa": 1014.1
        },
        "mq7": {
          "gas_raw": 123,
          "co_ppm": 124.7
        },
        "ds18b20": {
          "temperature_c": 28.9
        }
      },
      "actuators": {
        "rgb_led": {
          "state": "on",
          "color": "green"
        }
      }
    },
    {
      "deviceId": "ESP32-004",
      "nodeId": "NODE10",
      "gatewayId": "GW01",
      "ts": "2026-05-13T08:34:14.593Z",
      "seq": 18139,
      "rssi": -83,
      "battery": 3.83,
      "sensors": {
        "bmp280": {
          "temperature_c": 28.5,
          "pressure_hpa": 1013.2
        },
        "mq7": {
          "gas_raw": 133,
          "co_ppm": 135.7
        },
        "ds18b20": {
          "temperature_c": 28.6
        }
      },
      "actuators": {
        "rgb_led": {
          "state": "on",
          "color": "blue"
        }
      }
    },
    {
      "deviceId": "ESP32-004",
      "nodeId": "NODE10",
      "gatewayId": "GW01",
      "ts": "2026-05-13T08:34:19.596Z",
      "seq": 18140,
      "rssi": -83,
      "battery": 3.83,
      "sensors": {
        "bmp280": {
          "temperature_c": 27.6,
          "pressure_hpa": 1014.2
        },
        "mq7": {
          "gas_raw": 115,
          "co_ppm": 115.2
        },
        "ds18b20": {
          "temperature_c": 27.6
        }
      },
      "actuators": {
        "rgb_led": {
          "state": "on",
          "color": "red"
        }
      }
    },
    {
      "deviceId": "ESP32-004",
      "nodeId": "NODE10",
      "gatewayId": "GW01",
      "ts": "2026-05-13T08:34:24.602Z",
      "seq": 18141,
      "rssi": -85,
      "battery": 3.83,
      "sensors": {
        "bmp280": {
          "temperature_c": 27.2,
          "pressure_hpa": 1014.1
        },
        "mq7": {
          "gas_raw": 113,
          "co_ppm": 114.7
        },
        "ds18b20": {
          "temperature_c": 27.3
        }
      },
      "actuators": {
        "rgb_led": {
          "state": "off",
          "color": "off"
        }
      }
    },
    {
      "deviceId": "ESP32-004",
      "nodeId": "NODE10",
      "gatewayId": "GW01",
      "ts": "2026-05-13T08:34:29.603Z",
      "seq": 18142,
      "rssi": -84,
      "battery": 3.83,
      "sensors": {
        "bmp280": {
          "temperature_c": 28.3,
          "pressure_hpa": 1013.5
        },
        "mq7": {
          "gas_raw": 115,
          "co_ppm": 114.4
        },
        "ds18b20": {
          "temperature_c": 28.2
        }
      },
      "actuators": {
        "rgb_led": {
          "state": "on",
          "color": "green"
        }
      }
    },
    {
      "deviceId": "ESP32-004",
      "nodeId": "NODE10",
      "gatewayId": "GW01",
      "ts": "2026-05-13T08:34:34.610Z",
      "seq": 18143,
      "rssi": -85,
      "battery": 3.83,
      "sensors": {
        "bmp280": {
          "temperature_c": 27.5,
          "pressure_hpa": 1012.5
        },
        "mq7": {
          "gas_raw": 137,
          "co_ppm": 138.1
        },
        "ds18b20": {
          "temperature_c": 27.7
        }
      },
      "actuators": {
        "rgb_led": {
          "state": "on",
          "color": "blue"
        }
      }
    },
    {
      "deviceId": "ESP32-004",
      "nodeId": "NODE10",
      "gatewayId": "GW01",
      "ts": "2026-05-13T08:34:39.616Z",
      "seq": 18144,
      "rssi": -84,
      "battery": 3.83,
      "sensors": {
        "bmp280": {
          "temperature_c": 27.7,
          "pressure_hpa": 1012
        },
        "mq7": {
          "gas_raw": 124,
          "co_ppm": 126.6
        },
        "ds18b20": {
          "temperature_c": 27.7
        }
      },
      "actuators": {
        "rgb_led": {
          "state": "on",
          "color": "red"
        }
      }
    },
    {
      "deviceId": "ESP32-004",
      "nodeId": "NODE10",
      "gatewayId": "GW01",
      "ts": "2026-05-13T08:34:44.623Z",
      "seq": 18145,
      "rssi": -84,
      "battery": 3.83,
      "sensors": {
        "bmp280": {
          "temperature_c": 27.9,
          "pressure_hpa": 1013
        },
        "mq7": {
          "gas_raw": 124,
          "co_ppm": 120.1
        },
        "ds18b20": {
          "temperature_c": 27.9
        }
      },
      "actuators": {
        "rgb_led": {
          "state": "off",
          "color": "off"
        }
      }
    },
    {
      "deviceId": "ESP32-004",
      "nodeId": "NODE10",
      "gatewayId": "GW01",
      "ts": "2026-05-13T08:34:49.625Z",
      "seq": 18146,
      "rssi": -85,
      "battery": 3.83,
      "sensors": {
        "bmp280": {
          "temperature_c": 27.8,
          "pressure_hpa": 1012.5
        },
        "mq7": {
          "gas_raw": 133,
          "co_ppm": 131.5
        },
        "ds18b20": {
          "temperature_c": 27.9
        }
      },
      "actuators": {
        "rgb_led": {
          "state": "on",
          "color": "green"
        }
      }
    },
    {
      "deviceId": "ESP32-004",
      "nodeId": "NODE10",
      "gatewayId": "GW01",
      "ts": "2026-05-13T08:34:54.632Z",
      "seq": 18147,
      "rssi": -85,
      "battery": 3.83,
      "sensors": {
        "bmp280": {
          "temperature_c": 28.2,
          "pressure_hpa": 1014.1
        },
        "mq7": {
          "gas_raw": 116,
          "co_ppm": 115.2
        },
        "ds18b20": {
          "temperature_c": 28.3
        }
      },
      "actuators": {
        "rgb_led": {
          "state": "on",
          "color": "blue"
        }
      }
    },
    {
      "deviceId": "ESP32-004",
      "nodeId": "NODE10",
      "gatewayId": "GW01",
      "ts": "2026-05-13T08:34:59.636Z",
      "seq": 18148,
      "rssi": -86,
      "battery": 3.83,
      "sensors": {
        "bmp280": {
          "temperature_c": 28.7,
          "pressure_hpa": 1012.7
        },
        "mq7": {
          "gas_raw": 137,
          "co_ppm": 133.5
        },
        "ds18b20": {
          "temperature_c": 28.9
        }
      },
      "actuators": {
        "rgb_led": {
          "state": "on",
          "color": "red"
        }
      }
    },
    {
      "deviceId": "ESP32-004",
      "nodeId": "NODE10",
      "gatewayId": "GW01",
      "ts": "2026-05-13T08:35:04.645Z",
      "seq": 18149,
      "rssi": -86,
      "battery": 3.83,
      "sensors": {
        "bmp280": {
          "temperature_c": 27.6,
          "pressure_hpa": 1014.2
        },
        "mq7": {
          "gas_raw": 120,
          "co_ppm": 122.6
        },
        "ds18b20": {
          "temperature_c": 27.5
        }
      },
      "actuators": {
        "rgb_led": {
          "state": "off",
          "color": "off"
        }
      }
    },
    {
      "deviceId": "ESP32-004",
      "nodeId": "NODE10",
      "gatewayId": "GW01",
      "ts": "2026-05-13T08:35:09.651Z",
      "seq": 18150,
      "rssi": -86,
      "battery": 3.83,
      "sensors": {
        "bmp280": {
          "temperature_c": 28,
          "pressure_hpa": 1012
        },
        "mq7": {
          "gas_raw": 110,
          "co_ppm": 112.5
        },
        "ds18b20": {
          "temperature_c": 27.8
        }
      },
      "actuators": {
        "rgb_led": {
          "state": "on",
          "color": "green"
        }
      }
    },
    {
      "deviceId": "ESP32-004",
      "nodeId": "NODE10",
      "gatewayId": "GW01",
      "ts": "2026-05-13T08:35:14.657Z",
      "seq": 18151,
      "rssi": -85,
      "battery": 3.83,
      "sensors": {
        "bmp280": {
          "temperature_c": 27.7,
          "pressure_hpa": 1012.2
        },
        "mq7": {
          "gas_raw": 128,
          "co_ppm": 130.5
        },
        "ds18b20": {
          "temperature_c": 27.7
        }
      },
      "actuators": {
        "rgb_led": {
          "state": "on",
          "color": "blue"
        }
      }
    },
    {
      "deviceId": "ESP32-004",
      "nodeId": "NODE10",
      "gatewayId": "GW01",
      "ts": "2026-05-13T08:35:19.664Z",
      "seq": 18152,
      "rssi": -87,
      "battery": 3.83,
      "sensors": {
        "bmp280": {
          "temperature_c": 28.4,
          "pressure_hpa": 1014.1
        },
        "mq7": {
          "gas_raw": 112,
          "co_ppm": 115.7
        },
        "ds18b20": {
          "temperature_c": 28.6
        }
      },
      "actuators": {
        "rgb_led": {
          "state": "on",
          "color": "red"
        }
      }
    },
    {
      "deviceId": "ESP32-004",
      "nodeId": "NODE10",
      "gatewayId": "GW01",
      "ts": "2026-05-13T08:35:24.664Z",
      "seq": 18153,
      "rssi": -86,
      "battery": 3.83,
      "sensors": {
        "bmp280": {
          "temperature_c": 27.4,
          "pressure_hpa": 1012.5
        },
        "mq7": {
          "gas_raw": 113,
          "co_ppm": 112.1
        },
        "ds18b20": {
          "temperature_c": 27.4
        }
      },
      "actuators": {
        "rgb_led": {
          "state": "off",
          "color": "off"
        }
      }
    },
    {
      "deviceId": "ESP32-004",
      "nodeId": "NODE10",
      "gatewayId": "GW01",
      "ts": "2026-05-13T08:35:29.671Z",
      "seq": 18154,
      "rssi": -85,
      "battery": 3.83,
      "sensors": {
        "bmp280": {
          "temperature_c": 27.9,
          "pressure_hpa": 1012.3
        },
        "mq7": {
          "gas_raw": 123,
          "co_ppm": 123.2
        },
        "ds18b20": {
          "temperature_c": 27.6
        }
      },
      "actuators": {
        "rgb_led": {
          "state": "on",
          "color": "green"
        }
      }
    },
    {
      "deviceId": "ESP32-004",
      "nodeId": "NODE10",
      "gatewayId": "GW01",
      "ts": "2026-05-13T08:35:34.682Z",
      "seq": 18155,
      "rssi": -86,
      "battery": 3.83,
      "sensors": {
        "bmp280": {
          "temperature_c": 28.4,
          "pressure_hpa": 1013.4
        },
        "mq7": {
          "gas_raw": 109,
          "co_ppm": 111.7
        },
        "ds18b20": {
          "temperature_c": 28.2
        }
      },
      "actuators": {
        "rgb_led": {
          "state": "on",
          "color": "blue"
        }
      }
    },
    {
      "deviceId": "ESP32-004",
      "nodeId": "NODE10",
      "gatewayId": "GW01",
      "ts": "2026-05-13T08:35:39.684Z",
      "seq": 18156,
      "rssi": -84,
      "battery": 3.83,
      "sensors": {
        "bmp280": {
          "temperature_c": 28.1,
          "pressure_hpa": 1013.2
        },
        "mq7": {
          "gas_raw": 121,
          "co_ppm": 119.2
        },
        "ds18b20": {
          "temperature_c": 27.8
        }
      },
      "actuators": {
        "rgb_led": {
          "state": "on",
          "color": "red"
        }
      }
    },
    {
      "deviceId": "ESP32-004",
      "nodeId": "NODE10",
      "gatewayId": "GW01",
      "ts": "2026-05-13T08:35:44.691Z",
      "seq": 18157,
      "rssi": -83,
      "battery": 3.83,
      "sensors": {
        "bmp280": {
          "temperature_c": 27.9,
          "pressure_hpa": 1014
        },
        "mq7": {
          "gas_raw": 112,
          "co_ppm": 115.7
        },
        "ds18b20": {
          "temperature_c": 28
        }
      },
      "actuators": {
        "rgb_led": {
          "state": "off",
          "color": "off"
        }
      }
    },
    {
      "deviceId": "ESP32-004",
      "nodeId": "NODE10",
      "gatewayId": "GW01",
      "ts": "2026-05-13T08:35:49.691Z",
      "seq": 18158,
      "rssi": -84,
      "battery": 3.83,
      "sensors": {
        "bmp280": {
          "temperature_c": 27.4,
          "pressure_hpa": 1012.8
        },
        "mq7": {
          "gas_raw": 125,
          "co_ppm": 122.9
        },
        "ds18b20": {
          "temperature_c": 27.3
        }
      },
      "actuators": {
        "rgb_led": {
          "state": "on",
          "color": "green"
        }
      }
    },
    {
      "deviceId": "ESP32-004",
      "nodeId": "NODE10",
      "gatewayId": "GW01",
      "ts": "2026-05-13T08:35:54.691Z",
      "seq": 18159,
      "rssi": -86,
      "battery": 3.83,
      "sensors": {
        "bmp280": {
          "temperature_c": 27.9,
          "pressure_hpa": 1013.3
        },
        "mq7": {
          "gas_raw": 130,
          "co_ppm": 132.5
        },
        "ds18b20": {
          "temperature_c": 28
        }
      },
      "actuators": {
        "rgb_led": {
          "state": "on",
          "color": "blue"
        }
      }
    },
    {
      "deviceId": "ESP32-004",
      "nodeId": "NODE10",
      "gatewayId": "GW01",
      "ts": "2026-05-13T08:35:59.698Z",
      "seq": 18160,
      "rssi": -88,
      "battery": 3.83,
      "sensors": {
        "bmp280": {
          "temperature_c": 28.6,
          "pressure_hpa": 1012.6
        },
        "mq7": {
          "gas_raw": 104,
          "co_ppm": 102.1
        },
        "ds18b20": {
          "temperature_c": 28.8
        }
      },
      "actuators": {
        "rgb_led": {
          "state": "on",
          "color": "red"
        }
      }
    },
    {
      "deviceId": "ESP32-004",
      "nodeId": "NODE10",
      "gatewayId": "GW01",
      "ts": "2026-05-13T08:36:04.704Z",
      "seq": 18161,
      "rssi": -89,
      "battery": 3.83,
      "sensors": {
        "bmp280": {
          "temperature_c": 28.4,
          "pressure_hpa": 1013.2
        },
        "mq7": {
          "gas_raw": 103,
          "co_ppm": 105.5
        },
        "ds18b20": {
          "temperature_c": 28.5
        }
      },
      "actuators": {
        "rgb_led": {
          "state": "off",
          "color": "off"
        }
      }
    },
    {
      "deviceId": "ESP32-004",
      "nodeId": "NODE10",
      "gatewayId": "GW01",
      "ts": "2026-05-13T08:36:09.713Z",
      "seq": 18162,
      "rssi": -89,
      "battery": 3.83,
      "sensors": {
        "bmp280": {
          "temperature_c": 27.6,
          "pressure_hpa": 1011.8
        },
        "mq7": {
          "gas_raw": 113,
          "co_ppm": 112.4
        },
        "ds18b20": {
          "temperature_c": 27.6
        }
      },
      "actuators": {
        "rgb_led": {
          "state": "on",
          "color": "green"
        }
      }
    },
    {
      "deviceId": "ESP32-004",
      "nodeId": "NODE10",
      "gatewayId": "GW01",
      "ts": "2026-05-13T08:36:14.721Z",
      "seq": 18163,
      "rssi": -87,
      "battery": 3.83,
      "sensors": {
        "bmp280": {
          "temperature_c": 27.3,
          "pressure_hpa": 1013
        },
        "mq7": {
          "gas_raw": 103,
          "co_ppm": 104.5
        },
        "ds18b20": {
          "temperature_c": 27.2
        }
      },
      "actuators": {
        "rgb_led": {
          "state": "on",
          "color": "blue"
        }
      }
    },
    {
      "deviceId": "ESP32-004",
      "nodeId": "NODE10",
      "gatewayId": "GW01",
      "ts": "2026-05-13T08:36:19.725Z",
      "seq": 18164,
      "rssi": -87,
      "battery": 3.83,
      "sensors": {
        "bmp280": {
          "temperature_c": 28.4,
          "pressure_hpa": 1013.2
        },
        "mq7": {
          "gas_raw": 118,
          "co_ppm": 119.1
        },
        "ds18b20": {
          "temperature_c": 28.6
        }
      },
      "actuators": {
        "rgb_led": {
          "state": "on",
          "color": "red"
        }
      }
    },
    {
      "deviceId": "ESP32-004",
      "nodeId": "NODE10",
      "gatewayId": "GW01",
      "ts": "2026-05-13T08:36:24.732Z",
      "seq": 18165,
      "rssi": -87,
      "battery": 3.83,
      "sensors": {
        "bmp280": {
          "temperature_c": 27.3,
          "pressure_hpa": 1013.7
        },
        "mq7": {
          "gas_raw": 115,
          "co_ppm": 118.7
        },
        "ds18b20": {
          "temperature_c": 27.3
        }
      },
      "actuators": {
        "rgb_led": {
          "state": "off",
          "color": "off"
        }
      }
    },
    {
      "deviceId": "ESP32-004",
      "nodeId": "NODE10",
      "gatewayId": "GW01",
      "ts": "2026-05-13T08:36:29.732Z",
      "seq": 18166,
      "rssi": -85,
      "battery": 3.83,
      "sensors": {
        "bmp280": {
          "temperature_c": 28.9,
          "pressure_hpa": 1013
        },
        "mq7": {
          "gas_raw": 121,
          "co_ppm": 119.9
        },
        "ds18b20": {
          "temperature_c": 29.1
        }
      },
      "actuators": {
        "rgb_led": {
          "state": "on",
          "color": "green"
        }
      }
    },
    {
      "deviceId": "ESP32-004",
      "nodeId": "NODE10",
      "gatewayId": "GW01",
      "ts": "2026-05-13T08:36:34.732Z",
      "seq": 18167,
      "rssi": -85,
      "battery": 3.83,
      "sensors": {
        "bmp280": {
          "temperature_c": 27.9,
          "pressure_hpa": 1012
        },
        "mq7": {
          "gas_raw": 130,
          "co_ppm": 127.7
        },
        "ds18b20": {
          "temperature_c": 28.1
        }
      },
      "actuators": {
        "rgb_led": {
          "state": "on",
          "color": "blue"
        }
      }
    },
    {
      "deviceId": "ESP32-004",
      "nodeId": "NODE10",
      "gatewayId": "GW01",
      "ts": "2026-05-13T08:36:39.736Z",
      "seq": 18168,
      "rssi": -85,
      "battery": 3.83,
      "sensors": {
        "bmp280": {
          "temperature_c": 28.7,
          "pressure_hpa": 1013.3
        },
        "mq7": {
          "gas_raw": 106,
          "co_ppm": 107.4
        },
        "ds18b20": {
          "temperature_c": 28.9
        }
      },
      "actuators": {
        "rgb_led": {
          "state": "on",
          "color": "red"
        }
      }
    },
    {
      "deviceId": "ESP32-004",
      "nodeId": "NODE10",
      "gatewayId": "GW01",
      "ts": "2026-05-13T08:36:44.738Z",
      "seq": 18169,
      "rssi": -85,
      "battery": 3.83,
      "sensors": {
        "bmp280": {
          "temperature_c": 27.3,
          "pressure_hpa": 1012.5
        },
        "mq7": {
          "gas_raw": 122,
          "co_ppm": 124.5
        },
        "ds18b20": {
          "temperature_c": 27.6
        }
      },
      "actuators": {
        "rgb_led": {
          "state": "off",
          "color": "off"
        }
      }
    },
    {
      "deviceId": "ESP32-004",
      "nodeId": "NODE10",
      "gatewayId": "GW01",
      "ts": "2026-05-13T08:36:49.738Z",
      "seq": 18170,
      "rssi": -87,
      "battery": 3.83,
      "sensors": {
        "bmp280": {
          "temperature_c": 28.9,
          "pressure_hpa": 1013.5
        },
        "mq7": {
          "gas_raw": 121,
          "co_ppm": 118.3
        },
        "ds18b20": {
          "temperature_c": 29.1
        }
      },
      "actuators": {
        "rgb_led": {
          "state": "on",
          "color": "green"
        }
      }
    },
    {
      "deviceId": "ESP32-004",
      "nodeId": "NODE10",
      "gatewayId": "GW01",
      "ts": "2026-05-13T08:36:54.738Z",
      "seq": 18171,
      "rssi": -85,
      "battery": 3.83,
      "sensors": {
        "bmp280": {
          "temperature_c": 27.9,
          "pressure_hpa": 1013.8
        },
        "mq7": {
          "gas_raw": 114,
          "co_ppm": 118
        },
        "ds18b20": {
          "temperature_c": 27.6
        }
      },
      "actuators": {
        "rgb_led": {
          "state": "on",
          "color": "blue"
        }
      }
    },
    {
      "deviceId": "ESP32-004",
      "nodeId": "NODE10",
      "gatewayId": "GW01",
      "ts": "2026-05-13T08:36:59.738Z",
      "seq": 18172,
      "rssi": -84,
      "battery": 3.83,
      "sensors": {
        "bmp280": {
          "temperature_c": 27.8,
          "pressure_hpa": 1013.4
        },
        "mq7": {
          "gas_raw": 127,
          "co_ppm": 130.3
        },
        "ds18b20": {
          "temperature_c": 27.9
        }
      },
      "actuators": {
        "rgb_led": {
          "state": "on",
          "color": "red"
        }
      }
    },
    {
      "deviceId": "ESP32-004",
      "nodeId": "NODE10",
      "gatewayId": "GW01",
      "ts": "2026-05-13T08:37:04.744Z",
      "seq": 18173,
      "rssi": -85,
      "battery": 3.83,
      "sensors": {
        "bmp280": {
          "temperature_c": 28.7,
          "pressure_hpa": 1014.1
        },
        "mq7": {
          "gas_raw": 114,
          "co_ppm": 116
        },
        "ds18b20": {
          "temperature_c": 28.8
        }
      },
      "actuators": {
        "rgb_led": {
          "state": "off",
          "color": "off"
        }
      }
    },
    {
      "deviceId": "ESP32-004",
      "nodeId": "NODE10",
      "gatewayId": "GW01",
      "ts": "2026-05-13T08:37:09.745Z",
      "seq": 18174,
      "rssi": -83,
      "battery": 3.83,
      "sensors": {
        "bmp280": {
          "temperature_c": 28.4,
          "pressure_hpa": 1013.3
        },
        "mq7": {
          "gas_raw": 137,
          "co_ppm": 138.2
        },
        "ds18b20": {
          "temperature_c": 28.4
        }
      },
      "actuators": {
        "rgb_led": {
          "state": "on",
          "color": "green"
        }
      }
    },
    {
      "deviceId": "ESP32-004",
      "nodeId": "NODE10",
      "gatewayId": "GW01",
      "ts": "2026-05-13T08:37:14.751Z",
      "seq": 18175,
      "rssi": -83,
      "battery": 3.83,
      "sensors": {
        "bmp280": {
          "temperature_c": 27.6,
          "pressure_hpa": 1014.1
        },
        "mq7": {
          "gas_raw": 103,
          "co_ppm": 100
        },
        "ds18b20": {
          "temperature_c": 27.8
        }
      },
      "actuators": {
        "rgb_led": {
          "state": "on",
          "color": "blue"
        }
      }
    },
    {
      "deviceId": "ESP32-004",
      "nodeId": "NODE10",
      "gatewayId": "GW01",
      "ts": "2026-05-13T08:37:19.751Z",
      "seq": 18176,
      "rssi": -81,
      "battery": 3.83,
      "sensors": {
        "bmp280": {
          "temperature_c": 28.4,
          "pressure_hpa": 1012.1
        },
        "mq7": {
          "gas_raw": 122,
          "co_ppm": 121.7
        },
        "ds18b20": {
          "temperature_c": 28.2
        }
      },
      "actuators": {
        "rgb_led": {
          "state": "on",
          "color": "red"
        }
      }
    },
    {
      "deviceId": "ESP32-004",
      "nodeId": "NODE10",
      "gatewayId": "GW01",
      "ts": "2026-05-13T08:37:24.758Z",
      "seq": 18177,
      "rssi": -80,
      "battery": 3.83,
      "sensors": {
        "bmp280": {
          "temperature_c": 27.9,
          "pressure_hpa": 1012.5
        },
        "mq7": {
          "gas_raw": 127,
          "co_ppm": 129.4
        },
        "ds18b20": {
          "temperature_c": 27.9
        }
      },
      "actuators": {
        "rgb_led": {
          "state": "off",
          "color": "off"
        }
      }
    },
    {
      "deviceId": "ESP32-004",
      "nodeId": "NODE10",
      "gatewayId": "GW01",
      "ts": "2026-05-13T08:37:29.773Z",
      "seq": 18178,
      "rssi": -80,
      "battery": 3.83,
      "sensors": {
        "bmp280": {
          "temperature_c": 27.3,
          "pressure_hpa": 1013.3
        },
        "mq7": {
          "gas_raw": 109,
          "co_ppm": 109.8
        },
        "ds18b20": {
          "temperature_c": 27.2
        }
      },
      "actuators": {
        "rgb_led": {
          "state": "on",
          "color": "green"
        }
      }
    },
    {
      "deviceId": "ESP32-004",
      "nodeId": "NODE10",
      "gatewayId": "GW01",
      "ts": "2026-05-13T08:37:34.778Z",
      "seq": 18179,
      "rssi": -79,
      "battery": 3.83,
      "sensors": {
        "bmp280": {
          "temperature_c": 27.4,
          "pressure_hpa": 1012.3
        },
        "mq7": {
          "gas_raw": 112,
          "co_ppm": 108.4
        },
        "ds18b20": {
          "temperature_c": 27.4
        }
      },
      "actuators": {
        "rgb_led": {
          "state": "on",
          "color": "blue"
        }
      }
    },
    {
      "deviceId": "ESP32-004",
      "nodeId": "NODE10",
      "gatewayId": "GW01",
      "ts": "2026-05-13T08:37:39.785Z",
      "seq": 18180,
      "rssi": -81,
      "battery": 3.83,
      "sensors": {
        "bmp280": {
          "temperature_c": 27.5,
          "pressure_hpa": 1012.8
        },
        "mq7": {
          "gas_raw": 136,
          "co_ppm": 137.6
        },
        "ds18b20": {
          "temperature_c": 27.3
        }
      },
      "actuators": {
        "rgb_led": {
          "state": "on",
          "color": "red"
        }
      }
    },
    {
      "deviceId": "ESP32-004",
      "nodeId": "NODE10",
      "gatewayId": "GW01",
      "ts": "2026-05-13T08:37:44.785Z",
      "seq": 18181,
      "rssi": -81,
      "battery": 3.83,
      "sensors": {
        "bmp280": {
          "temperature_c": 28,
          "pressure_hpa": 1012.1
        },
        "mq7": {
          "gas_raw": 136,
          "co_ppm": 136.1
        },
        "ds18b20": {
          "temperature_c": 27.9
        }
      },
      "actuators": {
        "rgb_led": {
          "state": "off",
          "color": "off"
        }
      }
    },
    {
      "deviceId": "ESP32-004",
      "nodeId": "NODE10",
      "gatewayId": "GW01",
      "ts": "2026-05-13T08:37:49.785Z",
      "seq": 18182,
      "rssi": -80,
      "battery": 3.83,
      "sensors": {
        "bmp280": {
          "temperature_c": 27.9,
          "pressure_hpa": 1013.2
        },
        "mq7": {
          "gas_raw": 127,
          "co_ppm": 124.9
        },
        "ds18b20": {
          "temperature_c": 28.1
        }
      },
      "actuators": {
        "rgb_led": {
          "state": "on",
          "color": "green"
        }
      }
    },
    {
      "deviceId": "ESP32-004",
      "nodeId": "NODE10",
      "gatewayId": "GW01",
      "ts": "2026-05-13T08:37:54.785Z",
      "seq": 18183,
      "rssi": -78,
      "battery": 3.83,
      "sensors": {
        "bmp280": {
          "temperature_c": 27.9,
          "pressure_hpa": 1013.3
        },
        "mq7": {
          "gas_raw": 108,
          "co_ppm": 106.9
        },
        "ds18b20": {
          "temperature_c": 28.1
        }
      },
      "actuators": {
        "rgb_led": {
          "state": "on",
          "color": "blue"
        }
      }
    },
    {
      "deviceId": "ESP32-004",
      "nodeId": "NODE10",
      "gatewayId": "GW01",
      "ts": "2026-05-13T08:37:59.792Z",
      "seq": 18184,
      "rssi": -78,
      "battery": 3.83,
      "sensors": {
        "bmp280": {
          "temperature_c": 28.6,
          "pressure_hpa": 1013.6
        },
        "mq7": {
          "gas_raw": 108,
          "co_ppm": 109.2
        },
        "ds18b20": {
          "temperature_c": 28.4
        }
      },
      "actuators": {
        "rgb_led": {
          "state": "on",
          "color": "red"
        }
      }
    }
  ],
  "alerts": [
    {
      "id": "ALT-1778661479792-6036",
      "ts": "2026-05-13T08:37:59.792Z",
      "nodeId": "NODE10",
      "gatewayId": "GW01",
      "severity": "info",
      "rule": "low_light",
      "message": "Luminosidade muito baixa em NODE10: null%",
      "resolved": false
    },
    {
      "id": "ALT-1778661474785-48ae",
      "ts": "2026-05-13T08:37:54.785Z",
      "nodeId": "NODE10",
      "gatewayId": "GW01",
      "severity": "info",
      "rule": "low_light",
      "message": "Luminosidade muito baixa em NODE10: null%",
      "resolved": false
    },
    {
      "id": "ALT-1778661469785-0ea1",
      "ts": "2026-05-13T08:37:49.785Z",
      "nodeId": "NODE10",
      "gatewayId": "GW01",
      "severity": "info",
      "rule": "low_light",
      "message": "Luminosidade muito baixa em NODE10: null%",
      "resolved": false
    },
    {
      "id": "ALT-1778661464785-14bf",
      "ts": "2026-05-13T08:37:44.785Z",
      "nodeId": "NODE10",
      "gatewayId": "GW01",
      "severity": "info",
      "rule": "low_light",
      "message": "Luminosidade muito baixa em NODE10: null%",
      "resolved": false
    },
    {
      "id": "ALT-1778661459785-fcd3",
      "ts": "2026-05-13T08:37:39.785Z",
      "nodeId": "NODE10",
      "gatewayId": "GW01",
      "severity": "info",
      "rule": "low_light",
      "message": "Luminosidade muito baixa em NODE10: null%",
      "resolved": false
    },
    {
      "id": "ALT-1778661454779-f56c",
      "ts": "2026-05-13T08:37:34.779Z",
      "nodeId": "NODE10",
      "gatewayId": "GW01",
      "severity": "info",
      "rule": "low_light",
      "message": "Luminosidade muito baixa em NODE10: null%",
      "resolved": false
    },
    {
      "id": "ALT-1778661449773-7e7d",
      "ts": "2026-05-13T08:37:29.773Z",
      "nodeId": "NODE10",
      "gatewayId": "GW01",
      "severity": "info",
      "rule": "low_light",
      "message": "Luminosidade muito baixa em NODE10: null%",
      "resolved": false
    },
    {
      "id": "ALT-1778661444758-cf54",
      "ts": "2026-05-13T08:37:24.758Z",
      "nodeId": "NODE10",
      "gatewayId": "GW01",
      "severity": "info",
      "rule": "low_light",
      "message": "Luminosidade muito baixa em NODE10: null%",
      "resolved": false
    },
    {
      "id": "ALT-1778661439751-2eb2",
      "ts": "2026-05-13T08:37:19.752Z",
      "nodeId": "NODE10",
      "gatewayId": "GW01",
      "severity": "info",
      "rule": "low_light",
      "message": "Luminosidade muito baixa em NODE10: null%",
      "resolved": false
    },
    {
      "id": "ALT-1778661434751-89b3",
      "ts": "2026-05-13T08:37:14.751Z",
      "nodeId": "NODE10",
      "gatewayId": "GW01",
      "severity": "info",
      "rule": "low_light",
      "message": "Luminosidade muito baixa em NODE10: null%",
      "resolved": false
    },
    {
      "id": "ALT-1778661429745-5fa6",
      "ts": "2026-05-13T08:37:09.745Z",
      "nodeId": "NODE10",
      "gatewayId": "GW01",
      "severity": "info",
      "rule": "low_light",
      "message": "Luminosidade muito baixa em NODE10: null%",
      "resolved": false
    },
    {
      "id": "ALT-1778661424744-0e69",
      "ts": "2026-05-13T08:37:04.744Z",
      "nodeId": "NODE10",
      "gatewayId": "GW01",
      "severity": "info",
      "rule": "low_light",
      "message": "Luminosidade muito baixa em NODE10: null%",
      "resolved": false
    },
    {
      "id": "ALT-1778661419738-09f0",
      "ts": "2026-05-13T08:36:59.738Z",
      "nodeId": "NODE10",
      "gatewayId": "GW01",
      "severity": "info",
      "rule": "low_light",
      "message": "Luminosidade muito baixa em NODE10: null%",
      "resolved": false
    },
    {
      "id": "ALT-1778661414738-29c1",
      "ts": "2026-05-13T08:36:54.738Z",
      "nodeId": "NODE10",
      "gatewayId": "GW01",
      "severity": "info",
      "rule": "low_light",
      "message": "Luminosidade muito baixa em NODE10: null%",
      "resolved": false
    },
    {
      "id": "ALT-1778661409738-368e",
      "ts": "2026-05-13T08:36:49.738Z",
      "nodeId": "NODE10",
      "gatewayId": "GW01",
      "severity": "info",
      "rule": "low_light",
      "message": "Luminosidade muito baixa em NODE10: null%",
      "resolved": false
    },
    {
      "id": "ALT-1778661404738-7edb",
      "ts": "2026-05-13T08:36:44.738Z",
      "nodeId": "NODE10",
      "gatewayId": "GW01",
      "severity": "info",
      "rule": "low_light",
      "message": "Luminosidade muito baixa em NODE10: null%",
      "resolved": false
    },
    {
      "id": "ALT-1778661399736-4b4e",
      "ts": "2026-05-13T08:36:39.736Z",
      "nodeId": "NODE10",
      "gatewayId": "GW01",
      "severity": "info",
      "rule": "low_light",
      "message": "Luminosidade muito baixa em NODE10: null%",
      "resolved": false
    },
    {
      "id": "ALT-1778661394732-76bc",
      "ts": "2026-05-13T08:36:34.732Z",
      "nodeId": "NODE10",
      "gatewayId": "GW01",
      "severity": "info",
      "rule": "low_light",
      "message": "Luminosidade muito baixa em NODE10: null%",
      "resolved": false
    },
    {
      "id": "ALT-1778661389732-0e32",
      "ts": "2026-05-13T08:36:29.732Z",
      "nodeId": "NODE10",
      "gatewayId": "GW01",
      "severity": "info",
      "rule": "low_light",
      "message": "Luminosidade muito baixa em NODE10: null%",
      "resolved": false
    },
    {
      "id": "ALT-1778661384732-91d3",
      "ts": "2026-05-13T08:36:24.732Z",
      "nodeId": "NODE10",
      "gatewayId": "GW01",
      "severity": "info",
      "rule": "low_light",
      "message": "Luminosidade muito baixa em NODE10: null%",
      "resolved": false
    },
    {
      "id": "ALT-1778661379725-9b78",
      "ts": "2026-05-13T08:36:19.725Z",
      "nodeId": "NODE10",
      "gatewayId": "GW01",
      "severity": "info",
      "rule": "low_light",
      "message": "Luminosidade muito baixa em NODE10: null%",
      "resolved": false
    },
    {
      "id": "ALT-1778661374721-838f",
      "ts": "2026-05-13T08:36:14.721Z",
      "nodeId": "NODE10",
      "gatewayId": "GW01",
      "severity": "info",
      "rule": "low_light",
      "message": "Luminosidade muito baixa em NODE10: null%",
      "resolved": false
    },
    {
      "id": "ALT-1778661369713-ccab",
      "ts": "2026-05-13T08:36:09.713Z",
      "nodeId": "NODE10",
      "gatewayId": "GW01",
      "severity": "info",
      "rule": "low_light",
      "message": "Luminosidade muito baixa em NODE10: null%",
      "resolved": false
    },
    {
      "id": "ALT-1778661364704-799e",
      "ts": "2026-05-13T08:36:04.704Z",
      "nodeId": "NODE10",
      "gatewayId": "GW01",
      "severity": "info",
      "rule": "low_light",
      "message": "Luminosidade muito baixa em NODE10: null%",
      "resolved": false
    },
    {
      "id": "ALT-1778661359698-6251",
      "ts": "2026-05-13T08:35:59.698Z",
      "nodeId": "NODE10",
      "gatewayId": "GW01",
      "severity": "info",
      "rule": "low_light",
      "message": "Luminosidade muito baixa em NODE10: null%",
      "resolved": false
    },
    {
      "id": "ALT-1778661354691-6505",
      "ts": "2026-05-13T08:35:54.691Z",
      "nodeId": "NODE10",
      "gatewayId": "GW01",
      "severity": "info",
      "rule": "low_light",
      "message": "Luminosidade muito baixa em NODE10: null%",
      "resolved": false
    },
    {
      "id": "ALT-1778661349691-2395",
      "ts": "2026-05-13T08:35:49.691Z",
      "nodeId": "NODE10",
      "gatewayId": "GW01",
      "severity": "info",
      "rule": "low_light",
      "message": "Luminosidade muito baixa em NODE10: null%",
      "resolved": false
    },
    {
      "id": "ALT-1778661344691-de3d",
      "ts": "2026-05-13T08:35:44.691Z",
      "nodeId": "NODE10",
      "gatewayId": "GW01",
      "severity": "info",
      "rule": "low_light",
      "message": "Luminosidade muito baixa em NODE10: null%",
      "resolved": false
    },
    {
      "id": "ALT-1778661339684-934e",
      "ts": "2026-05-13T08:35:39.684Z",
      "nodeId": "NODE10",
      "gatewayId": "GW01",
      "severity": "info",
      "rule": "low_light",
      "message": "Luminosidade muito baixa em NODE10: null%",
      "resolved": false
    },
    {
      "id": "ALT-1778661334682-c29c",
      "ts": "2026-05-13T08:35:34.682Z",
      "nodeId": "NODE10",
      "gatewayId": "GW01",
      "severity": "info",
      "rule": "low_light",
      "message": "Luminosidade muito baixa em NODE10: null%",
      "resolved": false
    },
    {
      "id": "ALT-1778661329671-5480",
      "ts": "2026-05-13T08:35:29.671Z",
      "nodeId": "NODE10",
      "gatewayId": "GW01",
      "severity": "info",
      "rule": "low_light",
      "message": "Luminosidade muito baixa em NODE10: null%",
      "resolved": false
    },
    {
      "id": "ALT-1778661324664-e3b3",
      "ts": "2026-05-13T08:35:24.664Z",
      "nodeId": "NODE10",
      "gatewayId": "GW01",
      "severity": "info",
      "rule": "low_light",
      "message": "Luminosidade muito baixa em NODE10: null%",
      "resolved": false
    },
    {
      "id": "ALT-1778661319664-d7d7",
      "ts": "2026-05-13T08:35:19.664Z",
      "nodeId": "NODE10",
      "gatewayId": "GW01",
      "severity": "info",
      "rule": "low_light",
      "message": "Luminosidade muito baixa em NODE10: null%",
      "resolved": false
    },
    {
      "id": "ALT-1778661314657-99d4",
      "ts": "2026-05-13T08:35:14.657Z",
      "nodeId": "NODE10",
      "gatewayId": "GW01",
      "severity": "info",
      "rule": "low_light",
      "message": "Luminosidade muito baixa em NODE10: null%",
      "resolved": false
    },
    {
      "id": "ALT-1778661309651-9c6b",
      "ts": "2026-05-13T08:35:09.651Z",
      "nodeId": "NODE10",
      "gatewayId": "GW01",
      "severity": "info",
      "rule": "low_light",
      "message": "Luminosidade muito baixa em NODE10: null%",
      "resolved": false
    },
    {
      "id": "ALT-1778661304645-3a72",
      "ts": "2026-05-13T08:35:04.645Z",
      "nodeId": "NODE10",
      "gatewayId": "GW01",
      "severity": "info",
      "rule": "low_light",
      "message": "Luminosidade muito baixa em NODE10: null%",
      "resolved": false
    },
    {
      "id": "ALT-1778661299636-924f",
      "ts": "2026-05-13T08:34:59.636Z",
      "nodeId": "NODE10",
      "gatewayId": "GW01",
      "severity": "info",
      "rule": "low_light",
      "message": "Luminosidade muito baixa em NODE10: null%",
      "resolved": false
    },
    {
      "id": "ALT-1778661294632-f47b",
      "ts": "2026-05-13T08:34:54.632Z",
      "nodeId": "NODE10",
      "gatewayId": "GW01",
      "severity": "info",
      "rule": "low_light",
      "message": "Luminosidade muito baixa em NODE10: null%",
      "resolved": false
    },
    {
      "id": "ALT-1778661289625-e373",
      "ts": "2026-05-13T08:34:49.625Z",
      "nodeId": "NODE10",
      "gatewayId": "GW01",
      "severity": "info",
      "rule": "low_light",
      "message": "Luminosidade muito baixa em NODE10: null%",
      "resolved": false
    },
    {
      "id": "ALT-1778661284623-167e",
      "ts": "2026-05-13T08:34:44.623Z",
      "nodeId": "NODE10",
      "gatewayId": "GW01",
      "severity": "info",
      "rule": "low_light",
      "message": "Luminosidade muito baixa em NODE10: null%",
      "resolved": false
    },
    {
      "id": "ALT-1778661279616-4a54",
      "ts": "2026-05-13T08:34:39.616Z",
      "nodeId": "NODE10",
      "gatewayId": "GW01",
      "severity": "info",
      "rule": "low_light",
      "message": "Luminosidade muito baixa em NODE10: null%",
      "resolved": false
    },
    {
      "id": "ALT-1778661274610-813f",
      "ts": "2026-05-13T08:34:34.610Z",
      "nodeId": "NODE10",
      "gatewayId": "GW01",
      "severity": "info",
      "rule": "low_light",
      "message": "Luminosidade muito baixa em NODE10: null%",
      "resolved": false
    },
    {
      "id": "ALT-1778661269603-5de4",
      "ts": "2026-05-13T08:34:29.603Z",
      "nodeId": "NODE10",
      "gatewayId": "GW01",
      "severity": "info",
      "rule": "low_light",
      "message": "Luminosidade muito baixa em NODE10: null%",
      "resolved": false
    },
    {
      "id": "ALT-1778661264602-c617",
      "ts": "2026-05-13T08:34:24.602Z",
      "nodeId": "NODE10",
      "gatewayId": "GW01",
      "severity": "info",
      "rule": "low_light",
      "message": "Luminosidade muito baixa em NODE10: null%",
      "resolved": false
    },
    {
      "id": "ALT-1778661259596-da72",
      "ts": "2026-05-13T08:34:19.596Z",
      "nodeId": "NODE10",
      "gatewayId": "GW01",
      "severity": "info",
      "rule": "low_light",
      "message": "Luminosidade muito baixa em NODE10: null%",
      "resolved": false
    },
    {
      "id": "ALT-1778661254593-14b0",
      "ts": "2026-05-13T08:34:14.593Z",
      "nodeId": "NODE10",
      "gatewayId": "GW01",
      "severity": "info",
      "rule": "low_light",
      "message": "Luminosidade muito baixa em NODE10: null%",
      "resolved": false
    },
    {
      "id": "ALT-1778661249581-4225",
      "ts": "2026-05-13T08:34:09.581Z",
      "nodeId": "NODE10",
      "gatewayId": "GW01",
      "severity": "info",
      "rule": "low_light",
      "message": "Luminosidade muito baixa em NODE10: null%",
      "resolved": false
    },
    {
      "id": "ALT-1778661244575-31b5",
      "ts": "2026-05-13T08:34:04.575Z",
      "nodeId": "NODE10",
      "gatewayId": "GW01",
      "severity": "info",
      "rule": "low_light",
      "message": "Luminosidade muito baixa em NODE10: null%",
      "resolved": false
    },
    {
      "id": "ALT-1778661239573-e18f",
      "ts": "2026-05-13T08:33:59.573Z",
      "nodeId": "NODE10",
      "gatewayId": "GW01",
      "severity": "info",
      "rule": "low_light",
      "message": "Luminosidade muito baixa em NODE10: null%",
      "resolved": false
    },
    {
      "id": "ALT-1778661234560-bab2",
      "ts": "2026-05-13T08:33:54.560Z",
      "nodeId": "NODE10",
      "gatewayId": "GW01",
      "severity": "info",
      "rule": "low_light",
      "message": "Luminosidade muito baixa em NODE10: null%",
      "resolved": false
    }
  ],
  "commands": [
    {
      "commandId": "CMD-1777316768923-19c8",
      "deviceId": "ESP32-001",
      "nodeId": "NODE07",
      "gatewayId": "GW01",
      "ts": "2026-04-27T19:06:08.923Z",
      "seq": 1802,
      "action": "set_sampling_interval",
      "params": {
        "seconds": 300
      },
      "status": "acked",
      "ack": {
        "ts": "2026-04-27T19:06:10.125Z",
        "result": "ok",
        "detail": "Comando set_sampling_interval aplicado em NODE07"
      }
    }
  ],
  "metrics": {
    "ingested": 19376,
    "alertsRaised": 7283,
    "commandsSent": 1,
    "commandAcks": 1
  }
}